bod/__init__.py
bod-1.0.3.dist-info/LICENSE
bod-1.0.3.dist-info/METADATA
bod-1.0.3.dist-info/WHEEL
bod-1.0.3.dist-info/top_level.txt
bod-1.0.3.dist-info/RECORD
