Metadata-Version: 2.2
Name: bod
Version: 1.0.3
Summary: Text Blob and Object Dumper
Author-email: Aaron Edwards <bod-util@ebob9.com>
Project-URL: Homepage, https://github.com/ebob9/bod
Requires-Python: >=3.11
License-File: LICENSE
